tapioca_jarbas/__init__.py
tapioca_jarbas/resource_mapping.py
tapioca_jarbas/tapioca_jarbas.py
tapioca_jarbas-1.0.1.dist-info/LICENSE
tapioca_jarbas-1.0.1.dist-info/METADATA
tapioca_jarbas-1.0.1.dist-info/WHEEL
tapioca_jarbas-1.0.1.dist-info/top_level.txt
tapioca_jarbas-1.0.1.dist-info/RECORD
