Metadata-Version: 2.1
Name: tapioca-jarbas
Version: 1.0.1
Summary: jarbas API wrapper using tapioca
Home-page: https://github.com/daneoshiga/tapioca-jarbas
Author: Danilo Shiga
Author-email: daniloshiga@gmail.com
License: MIT
Keywords: jarbas
Platform: UNKNOWN
Classifier: Development Status :: 5 - Production/Stable
Classifier: Intended Audience :: Developers
Classifier: License :: OSI Approved :: MIT License
Classifier: Natural Language :: English
Classifier: Programming Language :: Python :: 3
Classifier: Programming Language :: Python :: 3.1
Classifier: Programming Language :: Python :: 3.2
Classifier: Programming Language :: Python :: 3.3
Classifier: Programming Language :: Python :: 3.4
Classifier: Programming Language :: Python :: 3.5
Requires-Dist: tapioca-wrapper (<2)
